LICENSE
MANIFEST.in
README.md
pyproject.toml
setup.cfg
setup.py
src/heel/__init__.py
src/heel/ss.py
src/heel.egg-info/PKG-INFO
src/heel.egg-info/SOURCES.txt
src/heel.egg-info/dependency_links.txt
src/heel.egg-info/top_level.txt
src/heel/haha/__init__.py
src/heel/haha/aa.py