Metadata-Version: 2.1
Name: heel
Version: 1.0.0
Summary: 这是一个测试打包上传的包！
Home-page: https://github.com/qcdh1234/python
Author: 秦
Author-email: 571169713@qq.com
License: UNKNOWN
Project-URL: Bug Tracker, https://github.com/qcdh1234/python/tree/master/pack_test_lib
Platform: UNKNOWN
Classifier: Programming Language :: Python :: 3
Classifier: License :: OSI Approved :: MIT License
Classifier: Operating System :: OS Independent
Requires-Python: >=3.6
